COPYING.txt
MANIFEST.in
README.txt
setup.py
fast/__init__.py
fast/base.py
fast/benchmarks.py
fast/files.py
fast/utils.py
fast/commands/__init__.py
fast/commands/base.py
fast_cli.egg-info/PKG-INFO
fast_cli.egg-info/SOURCES.txt
fast_cli.egg-info/dependency_links.txt
fast_cli.egg-info/entry_points.txt
fast_cli.egg-info/requires.txt
fast_cli.egg-info/top_level.txt