Metadata-Version: 1.1
Name: fast-cli
Version: 0.0.4
Summary: Command-line tool to test the optimizations performed to a program
Home-page: https://github.com/hacs/fast
Author: Héctor Ramón Jiménez, and Alvaro Espuña Buxo
Author-email: hector0193@gmail.com
License: UNKNOWN
Keywords: command,line,tool
Platform: UNKNOWN
Classifier: Programming Language :: Python
Classifier: Development Status :: 4 - Beta
Classifier: Topic :: Software Development :: Libraries :: Python Modules
